{
    "board": {
        "number of arms": 8,
        "arms width": 4,
        "circle": [
            "YELLOW,YELLOW,BLACK,BLACK,BLACK,BLACK,YELLOW,YELLOW",
            "BLUE,BLUE,RED,RED,RED,RED,BLUE,BLUE",
            "BLUE,BLACK,RED,YELLOW,BLUE,BLACK,RED,YELLOW"
        ],
        "arm": [
            "RED,YELLOW,BLUE,BLACK",
            "RED,YELLOW,BLUE,BLACK",
            "BLACK,YELLOW,BLUE,RED",
            "BLUE,BLACK,RED,YELLOW",
            "BLUE,RED,BLACK,YELLOW",
            "RED,BLUE,YELLOW,BLACK",
            "RED,BLUE,YELLOW,BLACK"
        ]
    }
}
